ghfc_utils/__init__.py
ghfc_utils/pgs.py
ghfc_utils/slivar_dnm.py
ghfc_utils/slivar_reannotator.py
ghfc_utils/pgs_modules/clean.py
ghfc_utils/pgs_modules/format.py
ghfc_utils/pgs_modules/format_all.py
ghfc_utils/pgs_modules/gctb_impute.py
ghfc_utils/pgs_modules/gctb_impute_all.py
ghfc_utils/pgs_modules/report.py
ghfc_utils/pgs_modules/sbayesrc.py
ghfc_utils/pgs_modules/sbayesrc_all.py
ghfc_utils/pgs_modules/status.py
ghfc_utils/pgs_modules/utils.py
ghfc_utils/pgs_modules/resources/formatbook.json
ghfc_utils/resources/impacts.yaml
ghfc_utils/resources/model.WGS.tsv.gz
ghfc_utils-0.1.13.dist-info/METADATA
ghfc_utils-0.1.13.dist-info/WHEEL
ghfc_utils-0.1.13.dist-info/entry_points.txt
ghfc_utils-0.1.13.dist-info/licenses/LICENSE
ghfc_utils-0.1.13.dist-info/RECORD
